yitorch/__init__.py
yitorch/__main__.py
yitorch/cli.py
yitorch/const.py
yitorch/enums.py
yitorch/exceptions.py
yitorch/log.py
yitorch/core/__init__.py
yitorch/shared/__init__.py
yitorch-0.1.0.dist-info/licenses/LICENSE
yitorch-0.1.0.dist-info/METADATA
yitorch-0.1.0.dist-info/WHEEL
yitorch-0.1.0.dist-info/top_level.txt
yitorch-0.1.0.dist-info/RECORD
