Metadata-Version: 2.4
Name: yitorch
Version: 0.1.0
Summary: Add your description here
Requires-Python: >=3.10
License-File: LICENSE
Requires-Dist: torch>=2.8.0
Requires-Dist: yitool>=0.1.0
Dynamic: license-file
